ADF/__init__.py
ADF/_version.py
ADF/aws_lambda_handlers.py
ADF/config.py
ADF/exceptions.py
ADF/funcs.py
ADF/components/__init__.py
ADF/components/columns/__init__.py
ADF/components/columns/abstract_column.py
ADF/components/columns/list_column.py
ADF/components/columns/pandas_column.py
ADF/components/columns/spark_column.py
ADF/components/columns/sql_column.py
ADF/components/data_structures/__init__.py
ADF/components/data_structures/abstract_data_structure.py
ADF/components/data_structures/list_data_structure.py
ADF/components/data_structures/pandas_data_structure.py
ADF/components/data_structures/spark_data_structure.py
ADF/components/data_structures/sql_data_structure.py
ADF/components/flow_config/__init__.py
ADF/components/flow_config/abstract_data_flow.py
ADF/components/flow_config/batch_dependency_handlers.py
ADF/components/flow_config/collection.py
ADF/components/flow_config/data_loaders.py
ADF/components/flow_config/flow_sequencers.py
ADF/components/flow_config/meta_handler.py
ADF/components/flow_config/misc.py
ADF/components/flow_config/steps.py
ADF/components/implementers/__init__.py
ADF/components/implementers/abstract_implementer.py
ADF/components/implementers/aws_implementer.py
ADF/components/implementers/local_implementers.py
ADF/components/implementers/subcommands.py
ADF/components/layer_transitions/__init__.py
ADF/components/layer_transitions/abstract_layer_transition.py
ADF/components/layer_transitions/aws_transitions.py
ADF/components/layer_transitions/local_layer_transition.py
ADF/components/layer_transitions/sql_layer_transitions.py
ADF/components/layers/__init__.py
ADF/components/layers/abstract_data_layer.py
ADF/components/layers/local_file_layers.py
ADF/components/layers/sql_layers.py
ADF/components/layers/aws_data_layers/__init__.py
ADF/components/layers/aws_data_layers/aws_athena_layer.py
ADF/components/layers/aws_data_layers/aws_emr_layer.py
ADF/components/layers/aws_data_layers/aws_lambda_layer.py
adf-0.1.2.dist-info/LICENSE.md
adf-0.1.2.dist-info/METADATA
adf-0.1.2.dist-info/WHEEL
adf-0.1.2.dist-info/top_level.txt
adf-0.1.2.dist-info/RECORD
