Metadata-Version: 2.1
Name: adf
Version: 0.1.2
Summary: Create infrastructure agnostic data processing pipelines
Author: Patrick El Hage
Author-email: patrickelhageuniv@gmail.com
License-File: LICENSE.md
Requires-Dist: Cython (>=0.29.32)
Requires-Dist: numpy (>=1.21.2)
Requires-Dist: pandas (<1.3.0,>=1.2.4)
Requires-Dist: pyarrow (>=4.0.1)
Requires-Dist: pyspark (>=3.1.1)
Requires-Dist: SQLAlchemy (<2.0.0,>=1.4.17)
Requires-Dist: sqlalchemy-redshift (>=0.8.5)
Requires-Dist: pyathena (>=2.14.0)
Requires-Dist: PyYAML (>=6.0)
Requires-Dist: psycopg2-binary (>=2.9.1)
Requires-Dist: boto3 (>=1.24.66)
Requires-Dist: croniter (>=1.3.4)
Requires-Dist: venv-pack (>=0.2.0)
Requires-Dist: boto3-stubs (>=1.24.66)
Requires-Dist: ipython (>=7.27.0)
Requires-Dist: black (>=22.10)
Requires-Dist: twine (>=4.0)
